setup.py
p2p/__init__.py
p2p/auth.py
p2p/cache.py
p2p/command.py
p2p/models.py
p2p/tests.py
p2p/utils.py
p2p.egg-info/PKG-INFO
p2p.egg-info/SOURCES.txt
p2p.egg-info/dependency_links.txt
p2p.egg-info/entry_points.txt
p2p.egg-info/requires.txt
p2p.egg-info/top_level.txt