Metadata-Version: 1.0
Name: p2p
Version: 1.4.4
Summary: Tribune Content Services API wrapper
Home-page: http://github.com/newsapps/p2p-python
Author: Ryan Mark, Tribune News Applications
Author-email: newsapps@tribune.com
License: MIT
Keywords: Development Status :: 4 - Beta,License :: OSI Approved :: MIT License,Operating System :: OS Independent,Programming Language :: Python,Topic :: Internet
Platform: UNKNOWN
